chuck-0.0.1.dist-info/DESCRIPTION.rst
chuck-0.0.1.dist-info/RECORD
chuck-0.0.1.dist-info/metadata.json
chuck-0.0.1.dist-info/pbr.json
chuck-0.0.1.dist-info/WHEEL
chuck-0.0.1.dist-info/METADATA
chuck-0.0.1.dist-info/top_level.txt
chuck/__init__.py
chuck/osc/__init__.py
chuck/osc/oscAPI.py
chuck/osc/OSC.py
