Metadata-Version: 2.0
Name: chuck
Version: 0.0.1
Summary: Library wrapper for music creation using ChucK
Home-page: https://github.com/Calysto/chuck
Author: Douglas S. Blank
Author-email: dblank@cs.brynmawr.edu
License: UNKNOWN
Platform: UNKNOWN
Classifier: Framework :: IPython
Classifier: License :: OSI Approved :: GNU Affero General Public License v3 or later (AGPLv3+)
Classifier: Programming Language :: Python :: 3
Requires-Dist: IPython (>=3.0)
